iotnode/__init__.py
iotnode/controller.py
iotnode/module.py
iotnode-0.1.2.dist-info/LICENSE
iotnode-0.1.2.dist-info/METADATA
iotnode-0.1.2.dist-info/WHEEL
iotnode-0.1.2.dist-info/top_level.txt
iotnode-0.1.2.dist-info/RECORD
