Metadata-Version: 2.1
Name: iotnode
Version: 0.1.2
Summary: Framework for running embedded code with multiple modular sources of data input/output
Home-page: https://github.com/blip2/iotnode
Author: Ben Hussey
Author-email: ben@blip2.net
License: UNKNOWN
Platform: UNKNOWN
Classifier: Programming Language :: Python :: 3
Classifier: License :: OSI Approved :: MIT License
Classifier: Operating System :: OS Independent
License-File: LICENSE
